mongokv.py
mongokv-0.4.dist-info/licenses/LICENSE
mongokv-0.4.dist-info/WHEEL
mongokv-0.4.dist-info/METADATA
mongokv-0.4.dist-info/RECORD
